[
    {
        "name": "0x0000",
        "description": "An online file hoster.",
        "url": "https://github.com/Supercolbat/0x0000",
        "tags": ["wip"]
    },
    {
        "name": "One Line Crawler",
        "description": "A web crawler written in one line.",
        "url": "https://github.com/Supercolbat/Oneline-Python-Crawler",
        "tags": ["wip"]
    },
    {
        "name": "RoBot",
        "description": "A framework for making chat-controlled Roblox bots.",
        "url": "https://github.com/Supercolbat/RoBot",
        "tags": ["wip"]
    },
    {
        "name": "Pythonista",
        "description": "A terminal written entirely in Python. Only supports Windows.",
        "url": "",
        "tags": ["wip"]
    },
    {
        "name": "SkyView",
        "description": "View a player's Hypixel Skyblock stats from your phone!",
        "url": "",
        "tags": ["wip"]
    }
]